[{"id":734458169,"title":"The Game","description":"With unparalleled access and cinematic flair, \u201cThe Game\u201d offers a tense, action-packed look at a referee during an international soccer match.","url":"https:\/\/vimeo.com\/734458169","upload_date":"2022-07-28 14:10:32","thumbnail_small":"https:\/\/i.vimeocdn.com\/video\/1477864058-aba70f2f1f25148c52613e22d7b8433791641885df8e47d07849b450177fdaf5-d_100x75","thumbnail_medium":"https:\/\/i.vimeocdn.com\/video\/1477864058-aba70f2f1f25148c52613e22d7b8433791641885df8e47d07849b450177fdaf5-d_200x150","thumbnail_large":"https:\/\/i.vimeocdn.com\/video\/1477864058-aba70f2f1f25148c52613e22d7b8433791641885df8e47d07849b450177fdaf5-d_640","user_id":21087649,"user_name":"NewYorker","user_url":"https:\/\/vimeo.com\/newyorker","user_portrait_small":"https:\/\/i.vimeocdn.com\/portrait\/68175820_30x30?subrect=294%2C63%2C814%2C583&r=cover","user_portrait_medium":"https:\/\/i.vimeocdn.com\/portrait\/68175820_75x75?subrect=294%2C63%2C814%2C583&r=cover","user_portrait_large":"https:\/\/i.vimeocdn.com\/portrait\/68175820_100x100?subrect=294%2C63%2C814%2C583&r=cover","user_portrait_huge":"https:\/\/i.vimeocdn.com\/portrait\/68175820_300x300?subrect=294%2C63%2C814%2C583&r=cover","stats_number_of_likes":10,"stats_number_of_plays":292,"stats_number_of_comments":3,"duration":1028,"width":1920,"height":1080,"tags":"","embed_privacy":"anywhere"},{"id":724840774,"title":"Black Midi - Sugar\/Tzu","description":"Music video for Black Midi @bmblackmidi<br \/>\n<br \/>\nFeaturing:<br \/>\nAssassin Christabel West<br \/>\nSun Tzu @joeydallascowboy<br \/>\nSun Sugar @akathegiant<br \/>\nMrs Tzu @maria.shhh<br \/>\nMrs Sugar @marfawest<br \/>\nReferee @osh_veda<br \/>\nAnnouncer @chimpgreep<br \/>\n<br \/>\nLONDON UNIT:<br \/>\nEP @daneherman<br \/>\nProducer @manoelachiabai<br \/>\nProduction Manager @alisa_trit <br \/>\nProduction Assistant @max_cutting<br \/>\nProduction Assistant @jamesdewinton<br \/>\nShadow Producer @visualbyouche<br \/>\n<br \/>\nDirector of Photography @jakescottdp<br \/>\n1st AC @samrawlings110<br \/>\n2nd AC @stephmariehornby<br \/>\nCamera Trainee @emantheartist<br \/>\n<br \/>\nGaffer @saadrani<br \/>\nElectricians Ed Cook, Cameron Houston, @chaymcgill<br \/>\nRigger Tom Gillings<br \/>\n<br \/>\nProduction Designer @bon.walsh<br \/>\nMask Maker\t@natashalawes<br \/>\nArt Assistant @joeyouens<br \/>\nArmourer Angie Galea<br \/>\nAnimal Wrangler Trevor & Barbara Smith<br \/>\n<br \/>\nSFX Prosthetic Designer @13fingerfx<br \/>\nSFX Assistant @bethleighsfx<br \/>\nHair @carlyroberts_<br \/>\nMuA @nicmarilyn<br \/>\nMuA Assistant @_laurenjeffrey<br \/>\nStyling @elllie.walker<br \/>\nStyling Assistnat Henry Hawksworth<br \/>\n<br \/>\n3rd AD @frankystone_<br \/>\nCasting Director @sam_franco<br \/>\n<br \/>\nLabel @roughtraderecords<br \/>\nProduction @friend_london<br \/>\n<br \/>\nAudience Members: Samuel Frigberg, Drew Ritchie, Arno Verano, Jason Shillingford, Pete Valente, Max McLachlan, Jonathan Edwards, Tom Whelehan, Alex Gou, Johanna Adde, Alice Bradley, Jane Marley<br \/>\n<br \/>\nBEIRUT UNIT:<br \/>\nProducer @ayaghosn<br \/>\nProduction Manager @gababji<br \/>\nAssociate Producer @jinanechaaya<br \/>\n<br \/>\nDirector of Photography @ramzihibri<br \/>\n<br \/>\nProduction Coordinator @christiangharios<br \/>\nProduction Assistant Raymond Baysari<br \/>\nLocation Manager @jadnehmeh & Rosette Stephan, @pinyourfilm<br \/>\nLocation Assistant Anthony Samaha<br \/>\n<br \/>\nPOST:<br \/>\nEditor @arthurmonsieur & @n0elpaul<br \/>\nColorist @belalhibri<br \/>\nVFX @miledboulos<br \/>\n<br \/>\nSpecial thanks to Malek Hosni @ramzihibri @rae_morris @fryars Tom & Calum, Souk El Ahad, @lucidpost @talasafie @lwmjacobs @nixthenix and vaseline","url":"https:\/\/vimeo.com\/724840774","upload_date":"2022-06-28 07:38:51","thumbnail_small":"https:\/\/i.vimeocdn.com\/video\/1463506313-394da69871fb46c3573fbf2e53f8ebb4d37cae596b02b8b6c409426b567889e8-d_100x75","thumbnail_medium":"https:\/\/i.vimeocdn.com\/video\/1463506313-394da69871fb46c3573fbf2e53f8ebb4d37cae596b02b8b6c409426b567889e8-d_200x150","thumbnail_large":"https:\/\/i.vimeocdn.com\/video\/1463506313-394da69871fb46c3573fbf2e53f8ebb4d37cae596b02b8b6c409426b567889e8-d_640","user_id":711038,"user_name":"Noel Paul","user_url":"https:\/\/vimeo.com\/noelpaul","user_portrait_small":"https:\/\/i.vimeocdn.com\/portrait\/30736681_30x30","user_portrait_medium":"https:\/\/i.vimeocdn.com\/portrait\/30736681_75x75","user_portrait_large":"https:\/\/i.vimeocdn.com\/portrait\/30736681_100x100","user_portrait_huge":"https:\/\/i.vimeocdn.com\/portrait\/30736681_300x300","stats_number_of_likes":141,"stats_number_of_plays":10522,"stats_number_of_comments":9,"duration":235,"width":1920,"height":1440,"tags":"","embed_privacy":"anywhere"},{"id":732628233,"title":"STICK - J.I.D & J.COLE (FT. KENNY MASON & SHECK WES) [OFFICIAL MUSIC VIDEO]","description":"had the honor to shoot this music video over a few days and be able create a strongly paced video for the music industry. <br \/>\n_______________________<br \/>\nDirectors: @waboosh & @onda\u00a0\u00a0<br \/>\nExecutive Producers: @simonchasalow, @austinbarbera, @davidwept<br \/>\nProducer: @idr_farah<br \/>\nDP: @cory.burmester<br \/>\n1st AD: #JohnMingalone<br \/>\nProduction Manager: @kingkza<br \/>\nProduction Coordinator: @invaderzena<br \/>\n1st AC (A CAM): @seanvelascododge<br \/>\n1st AC (B CAM): @hellahannah_<br \/>\n1st AC: @terranovafoto<br \/>\n2nd AC: @gerard.tejada<br \/>\nSteadicam: @steadical<br \/>\nGaffer: @recsquadtv<br \/>\nKey Grip: @sam_clegg, #RobertBenitez<br \/>\nBBE: #FranklinRicartSr<br \/>\nBBG: #LuisPedroza<br \/>\nDMX Board Op: @nyiphonedeveloper<br \/>\nProduction Designer: @ilananotilana<br \/>\nLeadman (On Set): @bizarretechie<br \/>\nArt Director\/Armorer: @colts.world <br \/>\nSet Dresser: @obilicity<br \/>\nSet Dresser: @b_cinematics_<br \/>\nSet Dresser: @cathchang<br \/>\nSet Dresser: @isabellaallyson<br \/>\nSet Decorator: @derekdavidh<br \/>\nOff Set Dresser: #AmonWaters<br \/>\nArt Coordinator: @jhaylamosley<br \/>\nAsst Art Coordinator: @haileemcclelland_<br \/>\nTruck PA: @kobe.benn<br \/>\nPA: @_artixan<br \/>\nPA: @rossginsberg<br \/>\nPA: @yooomass<br \/>\nCasting Director: @arionabeninato @collectivecasting<br \/>\nVHS: @a_ciggs<br \/>\nEditor: @cutbykenny<br \/>\nAdd\u2019t Editors: @kevinthevp @braydenahn @jacob.jpeg<br \/>\nVFX: @ricklancaster_<br \/>\nAdd\u2019t VFX: @jadensteinhoff<br \/>\nColorist: @josephbicknell<br \/>\nLabel: @dreamville<br \/>\nProduction Co: @sixtwentysixproductions x @theparallelagency","url":"https:\/\/vimeo.com\/732628233","upload_date":"2022-07-22 20:01:33","thumbnail_small":"https:\/\/i.vimeocdn.com\/video\/1474755605-a94be28efa2cb184d67e448cf6f99678bfa1e5ca0467d227d5f5fa2fa836774a-d_100x75","thumbnail_medium":"https:\/\/i.vimeocdn.com\/video\/1474755605-a94be28efa2cb184d67e448cf6f99678bfa1e5ca0467d227d5f5fa2fa836774a-d_200x150","thumbnail_large":"https:\/\/i.vimeocdn.com\/video\/1474755605-a94be28efa2cb184d67e448cf6f99678bfa1e5ca0467d227d5f5fa2fa836774a-d_640","user_id":5772197,"user_name":"ONDA","user_url":"https:\/\/vimeo.com\/ondaworld","user_portrait_small":"https:\/\/i.vimeocdn.com\/portrait\/74984956_30x30?subrect=546%2C1090%2C1277%2C1821&r=cover","user_portrait_medium":"https:\/\/i.vimeocdn.com\/portrait\/74984956_75x75?subrect=546%2C1090%2C1277%2C1821&r=cover","user_portrait_large":"https:\/\/i.vimeocdn.com\/portrait\/74984956_100x100?subrect=546%2C1090%2C1277%2C1821&r=cover","user_portrait_huge":"https:\/\/i.vimeocdn.com\/portrait\/74984956_300x300?subrect=546%2C1090%2C1277%2C1821&r=cover","stats_number_of_likes":74,"stats_number_of_plays":2225,"stats_number_of_comments":3,"duration":309,"width":3126,"height":2160,"tags":"","embed_privacy":"anywhere"},{"id":733476115,"title":"The Trails Before Us","description":"THE TRAILS BEFORE US follows 17-year-old Nigel James, a Din\u00e9 mountain biker, as he hosts the first Enduro race in the Navajo Nation. Through revitalizing livestock and wildlife trails on his grandparents\u2019 land, Nigel and a new generation of riders honor the connection to their land, community, and culture.<br \/>\n<br \/>\n<br \/>\nDirector - Fritz Bitsoie<br \/>\nDirector of Photography - Leo Maco<br \/>\nProducer - Emma Hsu Jackson <br \/>\nExecutive Producers - Luke Tate & Crista Garcia<br \/>\nEditor - Nico Bovat\u00a0<br \/>\nSound - Francisco N\u00fa\u00f1ez Capriles<br \/>\nAC - Brandon Ripp<br \/>\nGrip - Nima Khazaei<br \/>\nProduction Coordinator - Megan Wilson<br \/>\nDrone Camera Op - Luke Fitch <br \/>\nDrone Pilot  - Jeb Stewart<br \/>\nSet Photographer - Viktor Maco<br \/>\nOriginal Music - William Ryan Fritch<br \/>\nSound Design and Mix - Hansdale Hsu<br \/>\nColor - Carlos Flores<br \/>\nTitle Design - Moniker<br \/>\nTranslation - Joe H. Kee","url":"https:\/\/vimeo.com\/733476115","upload_date":"2022-07-26 00:00:14","thumbnail_small":"https:\/\/i.vimeocdn.com\/video\/1476044020-5953e8844483ac9379b1db44c8da837d98f5d7f34e672a4a23b0ee937b746f65-d_100x75","thumbnail_medium":"https:\/\/i.vimeocdn.com\/video\/1476044020-5953e8844483ac9379b1db44c8da837d98f5d7f34e672a4a23b0ee937b746f65-d_200x150","thumbnail_large":"https:\/\/i.vimeocdn.com\/video\/1476044020-5953e8844483ac9379b1db44c8da837d98f5d7f34e672a4a23b0ee937b746f65-d_640","user_id":9190295,"user_name":"Fritz Bitsoie","user_url":"https:\/\/vimeo.com\/fritzbitsoie","user_portrait_small":"https:\/\/i.vimeocdn.com\/portrait\/63870330_30x30","user_portrait_medium":"https:\/\/i.vimeocdn.com\/portrait\/63870330_75x75","user_portrait_large":"https:\/\/i.vimeocdn.com\/portrait\/63870330_100x100","user_portrait_huge":"https:\/\/i.vimeocdn.com\/portrait\/63870330_300x300","stats_number_of_likes":149,"stats_number_of_plays":7313,"stats_number_of_comments":12,"duration":769,"width":2048,"height":858,"tags":"mountain biking, biking, sports, navajo, native american, short doc, short documentary, sxsw, big sky","embed_privacy":"anywhere"},{"id":732092762,"title":"Nice Talking to You","description":"BAFTA Student Award Shortlist 2019<br \/>\nOfficial Selection South by Southwest 2019<br \/>\nOfficial Selection Palm Springs International Shortfest 2019<br \/>\nOfficial Selection HollyShorts 2019<br \/>\nOfficial Selection Hamptons International Film Festival 2019<br \/>\nOfficial Selection Encounters Film Festival 2019<br \/>\nKodak Gold Scholarship Award 2018<br \/>\nVimeo Best Director Award - Columbia University Film Festival 2018<br \/>\nRichard Haber Award for Best Comedy - Columbia University Film Festival 2018<br \/>\nBest Producer - Columbia University Film Festival 2018<br \/>\nIFP Audience Award - Columbia University Film Festival 2018<br \/>\nJury Selects - Columbia University Film Festival 2018<br \/>\nStudent Selects - Columbia University Film Festival 2018<br \/>\n<br \/>\nStarring Bane Fakih & Colin Bates<br \/>\nWriters: Saim Sadiq & Joe Capotorto<br \/>\nDirector: Saim Sadiq<br \/>\nProducer: Joe Capotorto<br \/>\nCinematography: Federico Spiazzi<br \/>\nAmerican Sign Language Coach: Hannah Ehrenberg<br \/>\nSign Language Consultant: Julia Silvestri<br \/>\nEditor: Saim Sadiq<br \/>\nAdditional Editor: Jasmin Tenucci<br \/>\nProduction Design: Markus Wulf<br \/>\nFirst Assistant Director: Maggie Briggs<br \/>\nCo-Producer: Federica Belleti<br \/>\nColor: Mikki Crisostomo<br \/>\nSound Recordist: Xixi Wang<br \/>\nSound Designer: Arjun Sheth <br \/>\nSound Mix: Ryan Billia<br \/>\nCamera Assistants: Jasmin Tenucci, Austin Hsieh & Rob Bellon<br \/>\n2nd Assistant Directors: Rodney Llaverias & Nathalie Alvarez Mesen<br \/>\nGaffer: Miguel Ortiz<br \/>\nGrip: Andrew Bell<br \/>\nMusic Supervisor: Jonathan Hecht<br \/>\n<br \/>\n<br \/>\nProduced in partial fulfilment of the MFA degree in Film at Columbia University School of the Arts<br \/>\n<br \/>\nIn association with the Program in the Education of the Deaf & Hard of Hearing at Teacher's College, Columbia University","url":"https:\/\/vimeo.com\/732092762","upload_date":"2022-07-21 09:01:54","thumbnail_small":"https:\/\/i.vimeocdn.com\/video\/1473604825-77a1986712758332e7e0c2d0a3d4eb33f8d6be6178e7a963c21cd5c6f03d483a-d_100x75","thumbnail_medium":"https:\/\/i.vimeocdn.com\/video\/1473604825-77a1986712758332e7e0c2d0a3d4eb33f8d6be6178e7a963c21cd5c6f03d483a-d_200x150","thumbnail_large":"https:\/\/i.vimeocdn.com\/video\/1473604825-77a1986712758332e7e0c2d0a3d4eb33f8d6be6178e7a963c21cd5c6f03d483a-d_640","user_id":34963407,"user_name":"Saim Sadiq","user_url":"https:\/\/vimeo.com\/user34963407","user_portrait_small":"https:\/\/i.vimeocdn.com\/portrait\/74944385_30x30?subrect=163%2C753%2C1126%2C1716&r=cover","user_portrait_medium":"https:\/\/i.vimeocdn.com\/portrait\/74944385_75x75?subrect=163%2C753%2C1126%2C1716&r=cover","user_portrait_large":"https:\/\/i.vimeocdn.com\/portrait\/74944385_100x100?subrect=163%2C753%2C1126%2C1716&r=cover","user_portrait_huge":"https:\/\/i.vimeocdn.com\/portrait\/74944385_300x300?subrect=163%2C753%2C1126%2C1716&r=cover","stats_number_of_likes":113,"stats_number_of_plays":16144,"stats_number_of_comments":13,"duration":1173,"width":2048,"height":1080,"tags":"","embed_privacy":"anywhere"},{"id":733182707,"title":"Rehearsal","description":"How do you stage a miracle healing? Protagonists are cast and different variations are tried out, improved and discarded. Boundaries dissolve between church and theatre, faith and credibility.<br \/>\n<br \/>\nCAST<br \/>\nRuby Akubueze <br \/>\nBrutus Richard <br \/>\nChimezie Imo <br \/>\nAmanda Oruh <br \/>\nNnadiekwe Paul<br \/>\nPeculiar Abonigbo<br \/>\nOdiaka Victor<br \/>\nOluwatoyin Olaiyewola<br \/>\nVanessa Zoe Daniels<br \/>\n<br \/>\n<br \/>\nCREW<br \/>\nWriter\/Director - Michael Omonua <br \/>\nCimematography - KC Obiajulu<br \/>\nProducer - DonPaul Umana <br \/>\n1st AD - Emmanuel Izuoba <br \/>\nSound - Tolulope Emmanuel Adesoji <br \/>\nWardrobe Demiji Sadik<br \/>\nArt Direction - Ogbeyemi Sunday<br \/>\nGaffer - Matolight<br \/>\n1st AC - Micah Anusiem<br \/>\nMake Up - Vanessa Oghozor<br \/>\nKey Grip - Idris Shokanbi<br \/>\nScript Translation - Felix Olaitan<br \/>\nColourist - Seun Opabisi<br \/>\nSound Design - Lyabo Solanke<br \/>\nBest Boy - Edward Ebenne Ekiko & Simon Yusuf<br \/>\nCamtech - Thompson Al-Hassan<br \/>\nAssistant Grip - Wada Celestine<br \/>\nAssist Art Direction - Oguntauase Tosin<br \/>\nFocus Puller - Micah Anusiem & Thad Yanongu<br \/>\nAstera Operator - Ogunkoya Abdulwasiu<br \/>\nScript Supervisor - Isadare Samsom Psalm<br \/>\n2nd AC - Kingsley E. Mmadu<br \/>\nBoom Op - Richard Effiom Bassey<br \/>\nEditor - Michael Omonua<br \/>\nStills Photography - Isaac Okorie<br \/>\nProduction Assistants - Iyanda Abioye & Isaac Obinna Ikeriogwuo<br \/>\n<br \/>\n<br \/>\nOFFICIAL SELECTION:<br \/>\nBerlinale Shorts 2021 (World Premiere)<br \/>\nKurzfilmtage Winterthur (Winner Oscar Qualifying Grand Prize for Best International Short Film)<br \/>\nCinema Jove (Winner Luna De Valencia Award for Best Short Film)<br \/>\nPanorama XVII Film Festival (Winner Best International Short Film)<br \/>\nChicago International Film Festival 2021<br \/>\nEncounters Film Festival 2021<br \/>\nPalm Springs ShortFest 2021<br \/>\nFestival De Cine Africano 2021<br \/>\nLago Film Festival 2021<br \/>\nDurban International Film Festival 2021<br \/>\nSemana De Cinema Negro 2021<br \/>\nAfrica In Motion Film Festival 2021<br \/>\nAfrika Film Festival Koln 2021<br \/>\nSundsvall International Film Festival 2021<br \/>\nLobo Festival 2021<br \/>\nCinemAfrica Film Festival 2021<br \/>\nFestival Court Derriere 2021<br \/>\nNBO Film Festival 2021<br \/>\nS16 Film Festival 2021<br \/>\nMadrid Shorts Week 2021<br \/>\nFilmfest Dresden 2022<br \/>\nKurzfilmwoche Regensburg 2022<br \/>\nFestival Regard 2022<br \/>\nFestival Psarokokalo 2022<br \/>\nLeiden Shorts 2022<br \/>\nA Kiss in the Desert 2022<br \/>\nLichter Filmfest Frankfurt International 2022<br \/>\n<br \/>\nmichaelomonua.com<br \/>\n<br \/>\nCine9ja Ent Ltd","url":"https:\/\/vimeo.com\/733182707","upload_date":"2022-07-25 06:53:40","thumbnail_small":"https:\/\/i.vimeocdn.com\/video\/1475519898-b72f439ff96ad59d39c3af10d2efefa11e5d46767521e165cfd576b659556d64-d_100x75","thumbnail_medium":"https:\/\/i.vimeocdn.com\/video\/1475519898-b72f439ff96ad59d39c3af10d2efefa11e5d46767521e165cfd576b659556d64-d_200x150","thumbnail_large":"https:\/\/i.vimeocdn.com\/video\/1475519898-b72f439ff96ad59d39c3af10d2efefa11e5d46767521e165cfd576b659556d64-d_640","user_id":1898197,"user_name":"Michael Gouken Omonua","user_url":"https:\/\/vimeo.com\/cine9ja","user_portrait_small":"https:\/\/i.vimeocdn.com\/portrait\/74982201_30x30","user_portrait_medium":"https:\/\/i.vimeocdn.com\/portrait\/74982201_75x75","user_portrait_large":"https:\/\/i.vimeocdn.com\/portrait\/74982201_100x100","user_portrait_huge":"https:\/\/i.vimeocdn.com\/portrait\/74982201_300x300","stats_number_of_likes":117,"stats_number_of_plays":9078,"stats_number_of_comments":13,"duration":873,"width":1920,"height":1080,"tags":"play, stage, theatre, religion, mike gouken, nollywood, nigerian cinema, amanda oruh, chimezie imo, brutus richard, ruby akubueze, berlinale, nigeria, michael omonua, short film, rehearsal","embed_privacy":"anywhere"},{"id":732539259,"title":"bloom","description":"A couple years ago, Ian and I were in Oakland for a commercial and decided to shoot a short on our down day. Bloom is about defying odds and stereotypes. It's through the cracks, that we can begin to see the light. Embody the grit your roots provided and find your own path to bloom.<br \/>\n<br \/>\nTo my friend, Hassan Galedary. Thank you for your writing, your truth, and sharing a bit about your journey with me. It has been awesome to hear about where you started and how you have grown. <br \/>\n<br \/>\nShout out to some of the other creative minds that helped make it happen -<br \/>\nProducer: Alun Lee<br \/>\nDP: Ian Rigby <br \/>\n1st AC: Allan Chavarria<br \/>\nCamera Car: Ultimate Arm <br \/>\nEdit: Alex Morrison<br \/>\nSound Design: Roman Richard<br \/>\nColor: Joseph Bicknell, Company 3<br \/>\nCasting\/Fixer: Adrian Burrell<br \/>\n<br \/>\nAnd to the talent that came out to be a part of this - <br \/>\nDog Trainer: Jas Leverette, Canine Intervention<br \/>\nMotorcycles: Nick Leonetti, Buddy Suttle, Kade Gates<br \/>\nBicycle: Lamar Designer<br \/>\nLow Rider: Adrian Burrell, Hongry<br \/>\nFire Scene: Ben Z1no","url":"https:\/\/vimeo.com\/732539259","upload_date":"2022-07-22 13:27:03","thumbnail_small":"https:\/\/i.vimeocdn.com\/video\/1474139984-e0d35a95a1bef84ba7996114b7ca649dfd4a8cced8547ffe528b2e7cd87377e2-d_100x75","thumbnail_medium":"https:\/\/i.vimeocdn.com\/video\/1474139984-e0d35a95a1bef84ba7996114b7ca649dfd4a8cced8547ffe528b2e7cd87377e2-d_200x150","thumbnail_large":"https:\/\/i.vimeocdn.com\/video\/1474139984-e0d35a95a1bef84ba7996114b7ca649dfd4a8cced8547ffe528b2e7cd87377e2-d_640","user_id":88222069,"user_name":"Trevor Paperny","user_url":"https:\/\/vimeo.com\/trevorpaperny","user_portrait_small":"https:\/\/i.vimeocdn.com\/portrait\/74978146_30x30?subrect=0%2C0%2C150%2C150&r=cover","user_portrait_medium":"https:\/\/i.vimeocdn.com\/portrait\/74978146_75x75?subrect=0%2C0%2C150%2C150&r=cover","user_portrait_large":"https:\/\/i.vimeocdn.com\/portrait\/74978146_100x100?subrect=0%2C0%2C150%2C150&r=cover","user_portrait_huge":"https:\/\/i.vimeocdn.com\/portrait\/74978146_300x300?subrect=0%2C0%2C150%2C150&r=cover","stats_number_of_likes":359,"stats_number_of_plays":6908,"stats_number_of_comments":14,"duration":93,"width":3840,"height":2160,"tags":"","embed_privacy":"anywhere"},{"id":719774611,"title":"WELCOME TO THE PROS | Lewis 'Poochi' Van Poetsch","description":"Lewis \u2018Poochi\u2019 Van Poetsch is a professional boxer. He has fought 150+ times with a record of 10 wins, 3 draws and 140+ losses. On paper, and in pure numbers, this record looks horrendous and that Poochi is an inadequate fighter but this is not the real story. Poochi is a \u2018Journeyman\u2019, or a more honest term might be a \u2018professional loser\u2019. In this short portrait 'Poochi' explains how he fell into the role, as he prepares for another weekend fight.<br \/>\n<br \/>\nShot in Birmingham, UK.<br \/>\n<br \/>\nDirected and Edited by Robin Mason<br \/>\nCinematography by David Bird<br \/>\nGraded by Alex Gregory @No.8 London<br \/>\nMusic by Christian Wade @Music Bed<br \/>\n<br \/>\nWith thanks to Pat Benson Boxing, No.8 London, Harri Kamalanathan, Phil Myers, Jon Hatch, Brendan Harvey, Alex Mills, Musicbed.","url":"https:\/\/vimeo.com\/719774611","upload_date":"2022-06-13 04:52:31","thumbnail_small":"https:\/\/i.vimeocdn.com\/video\/1464422547-763ca79f2a01c925bb1fd766692b10f8a63a7650c9416df62f94c901b28e0a66-d_100x75","thumbnail_medium":"https:\/\/i.vimeocdn.com\/video\/1464422547-763ca79f2a01c925bb1fd766692b10f8a63a7650c9416df62f94c901b28e0a66-d_200x150","thumbnail_large":"https:\/\/i.vimeocdn.com\/video\/1464422547-763ca79f2a01c925bb1fd766692b10f8a63a7650c9416df62f94c901b28e0a66-d_640","user_id":24036210,"user_name":"Robin Mason","user_url":"https:\/\/vimeo.com\/robinmason","user_portrait_small":"https:\/\/i.vimeocdn.com\/portrait\/23263918_30x30","user_portrait_medium":"https:\/\/i.vimeocdn.com\/portrait\/23263918_75x75","user_portrait_large":"https:\/\/i.vimeocdn.com\/portrait\/23263918_100x100","user_portrait_huge":"https:\/\/i.vimeocdn.com\/portrait\/23263918_300x300","stats_number_of_likes":230,"stats_number_of_plays":22273,"stats_number_of_comments":45,"duration":384,"width":1920,"height":1080,"tags":"Fight, england, UK, Journeyman, Film, Documentary, Doco, Short, Boxing, Poochi, Lewis Van Poetsch, Welcome to the pros","embed_privacy":"anywhere"},{"id":731865515,"title":"ODESZA - Light Of Day (feat. \u00d3lafur Arnalds) - Official Video","description":"Production Company: Blinkink<br \/>\nDirector: Bal\u00e1zs Simon <br \/>\nExecutive Producer: Josef Byrne<br \/>\nProducer: M\u00e1t\u00e9 Barbalics<br \/>\nHead of Production: Alex Halley<br \/>\n<br \/>\nConcept & ODESZA creative:<br \/>\nLuke Tanaka<br \/>\nSean Kusanagi<br \/>\n<br \/>\nShooting Team<br \/>\nDop: Max Halstead<br \/>\nStop Motion Producer: Sami Goddard<br \/>\nArt Director: Brin Frost<br \/>\nStudio: Clapham Road Studios<br \/>\nStudio Manager: Daisy Garside<br \/>\nArt Dept: Beattie Hartley<br \/>\n<br \/>\nPost Production Team<br \/>\nArt Director: P\u00e9ter K\u00e1ntor (Greenroom)<br \/>\nLead Previs Artist: Dane Armour<br \/>\nPrevis Artist: <br \/>\nJonathan Meret<br \/>\nD\u00e1vid Dell'Edera<br \/>\nCharacter Sculpting: L\u00e1szl\u00f3 Aszal\u00f3s<br \/>\nLead Compositor: Doma Harkai<br \/>\nCompositor: Adri\u00e1n Majoros<br \/>\nCompositor: Csaba B\u00e1lint<br \/>\nGraphic Artist: Andr\u00e1s Gunda<br \/>\nColorist: Szil\u00e1rd T\u00f6tszegi<br \/>\nDancer: Bea Egyed<br \/>\nSound Design: Jacob Wheeler<br \/>\nStoryboard: Mysie Pereira<br \/>\n<br \/>\nSunnyside Animation<br \/>\nProducer: D\u00e1niel Szab\u00f3<br \/>\nRigging TD: Holl\u00f3sy Zolt\u00e1n<br \/>\nCharacter Animation: <br \/>\nD\u00e1niel Szab\u00f3<br \/>\nBarcsay Marcell<br \/>\nGy\u00f6rgy F\u00e1bos<br \/>\nMocap Recording: Gergely R\u00e1cz<br \/>\nBlendshape Artist: J\u00e1nos Cs\u00e1sz\u00e1r<br \/>\n<br \/>\nJumpcut<br \/>\nProducer: \u00c1d\u00e1m Gy\u00f6rgy<br \/>\nLead Compositor: Bal\u00e1zs Seress<br \/>\nCompositing: <br \/>\nSzabolcs P\u00e1l<br \/>\nD\u00e1vid Velenczei<br \/>\n<br \/>\nUmbrella<br \/>\nProducer: Mikl\u00f3s K\u00e1zm\u00e9r<br \/>\n3D Assets: Battore Haraszti<br \/>\nCompositing: <br \/>\nD\u00e1niel Streer<br \/>\nCec\u00edlia Deszk<br \/>\n<br \/>\nGYAR<br \/>\nProducer: R\u00f3bert Erd\u00e9lyi<br \/>\nVFX Producer: Andr\u00e1s Piroska <br \/>\nHead of CGI: \u00c1ron Hargitay<br \/>\nCGI Supervisor: S\u00e1ndor Garaczi<br \/>\nHoudini Technical Director: \u00c1d\u00e1m Marih\u00e1zi<br \/>\nHoudini Artist: <br \/>\nZolt\u00e1n Mark\u00f3<br \/>\nSzabolcs Mazsari<br \/>\nIstv\u00e1n Bori<br \/>\nG\u00e1bor R\u00e1kossy<br \/>\nIv\u00e1n V\u00f6r\u00f6s<br \/>\nCGI Generalist: Gyula N\u00e9medi<br \/>\nCompositing: <br \/>\nHosseini Shahab<br \/>\nBal\u00e1zs Lublov\u00e1ry <br \/>\n\u00c1ron N\u00e9meti<br \/>\nKrist\u00f3f Ga\u00e1l<br \/>\nViktor Milt\u00e9nyi<br \/>\n<br \/>\nSpecial Thanks:<br \/>\nStephen McNally<br \/>\nGyula Sziklafy<br \/>\nFamily","url":"https:\/\/vimeo.com\/731865515","upload_date":"2022-07-20 15:58:35","thumbnail_small":"https:\/\/i.vimeocdn.com\/video\/1472886228-bcd3e202dd2425fc32a58bdaaf62bc032868c4f4dfc62e08ae0c575fe0698a30-d_100x75","thumbnail_medium":"https:\/\/i.vimeocdn.com\/video\/1472886228-bcd3e202dd2425fc32a58bdaaf62bc032868c4f4dfc62e08ae0c575fe0698a30-d_200x150","thumbnail_large":"https:\/\/i.vimeocdn.com\/video\/1472886228-bcd3e202dd2425fc32a58bdaaf62bc032868c4f4dfc62e08ae0c575fe0698a30-d_640","user_id":25615210,"user_name":"Bal\u00e1zs Simon","user_url":"https:\/\/vimeo.com\/balazss","user_portrait_small":"https:\/\/i.vimeocdn.com\/portrait\/9217836_30x30","user_portrait_medium":"https:\/\/i.vimeocdn.com\/portrait\/9217836_75x75","user_portrait_large":"https:\/\/i.vimeocdn.com\/portrait\/9217836_100x100","user_portrait_huge":"https:\/\/i.vimeocdn.com\/portrait\/9217836_300x300","stats_number_of_likes":554,"stats_number_of_plays":27219,"stats_number_of_comments":34,"duration":240,"width":2578,"height":1080,"tags":"motion capture, experimental, 2d, 3d, animation, cgi, painterly","embed_privacy":"anywhere"},{"id":724918260,"title":"This is Home - Kurt Sorge | SHIMANO","description":"Just downriver from Nelson, British Columbia, professional freerider Kurt Sorge has hand-crafted a compound that dreams are made of. Originally designed to progress his freeride career, Kurt's backyard has become not only a world-class proving ground for local freeriding hopefuls but also a way to reflect on the simple pleasures in life. After traveling the world for many years and competing at the highest levels, Kurt returns home to B.C. to find peace and solace in the mountains.<br \/>\n<br \/>\nReally big jumps, a small cabin, and mountains as far as the eye can see are all Kurt really needs for his humble existence. Addicted to the unlimited hang time and vast mountainous terrain, it's clear that Kurt has found his place in this world. Huge trains on the backyard jumps, solo freeriding deep in the mountains, and a quick dip in the local creek, This is Home.<br \/>\n<br \/>\nDirected by: Harrison Mendel<br \/>\nCinematography: Liam Mullany and Harrison Mendel<br \/>\n1st AC: Noah Dorsey<br \/>\nEdited By: David Peacock<br \/>\nColour: Sam Gilling <br \/>\nSound Design: Racket Sound, Jason Chiodo<br \/>\nVFX and Titles: Studio Dialog, Shelley Fried, Robb Thompson<br \/>\nScore: Andrew Judah\u00a0<br \/>\nMusic: \"What Went Down: Performed by Foals. Courtesy of Warner Music UK Ltd. By arrangement with Warner Music Group Film & TV Licensing <br \/>\nStill Photography: Sterling Lorence <br \/>\nSpecial Thanks: Chiara Durfeld, Rick Schnieder, Garett Buehler, Jackson Buehler, Kris McMechan, Retallack Lodge, Phil Pinfold, Rylan Bokstrom, Viktors Vilk, Johnny Smoke, The Dude, Drew Buckets, The Sacred Ride","url":"https:\/\/vimeo.com\/724918260","upload_date":"2022-06-28 11:09:27","thumbnail_small":"https:\/\/i.vimeocdn.com\/video\/1472704928-1f01c027d9bb98508c9430c291090348fe0f39dd8e5a7011e649db6da6c1e21e-d_100x75","thumbnail_medium":"https:\/\/i.vimeocdn.com\/video\/1472704928-1f01c027d9bb98508c9430c291090348fe0f39dd8e5a7011e649db6da6c1e21e-d_200x150","thumbnail_large":"https:\/\/i.vimeocdn.com\/video\/1472704928-1f01c027d9bb98508c9430c291090348fe0f39dd8e5a7011e649db6da6c1e21e-d_640","user_id":19780599,"user_name":"Ride Shimano","user_url":"https:\/\/vimeo.com\/rideshimano","user_portrait_small":"https:\/\/i.vimeocdn.com\/portrait\/10785328_30x30","user_portrait_medium":"https:\/\/i.vimeocdn.com\/portrait\/10785328_75x75","user_portrait_large":"https:\/\/i.vimeocdn.com\/portrait\/10785328_100x100","user_portrait_huge":"https:\/\/i.vimeocdn.com\/portrait\/10785328_300x300","stats_number_of_likes":417,"stats_number_of_plays":29308,"stats_number_of_comments":32,"duration":497,"width":3840,"height":1600,"tags":"Freeride, Sorge, Backyard, Rampage, Mountain Bike, MTB, British Columbia, Liam Mullany, TIH, Kurt Sorge, This is Home, Harrison Mendel, Nelson, Bike, Cycling, Extreme Sports, Retallack, Kootenays, Shimano, Biking","embed_privacy":"anywhere"},{"id":731378604,"title":"ADIDAS FT. RICK & MORTY - X SPEEDPORTAL","description":"TBWA\\NEBOKO <br \/>\nExecutive Creative Director: Thierry Albert <br \/>\nCreative Director: Thomas Jullien<br \/>\nArt Director: Jeremy Pedro <br \/>\nCopywriter: Toby Castle-Smith <br \/>\nBusiness Director: Valdemar Domingos <br \/>\nBrand Director: Codruta Arbore  <br \/>\nBrand Manager: Emma Chote <br \/>\nBrand Coordinator: Marco Baldasso  <br \/>\nExecutive Producer: Rosemarie Praaning <br \/>\nSenior Producer: Elise Hagedoorn <br \/>\nProducer: Aaron Mc Enaney  <br \/>\nStrategy: Lauren Mcilroy & Charlier Wright<br \/>\nSenior Designer: Maria Rull  <br \/>\nDesigner: Iolo Wynn Cowell  <br \/>\n<br \/>\nadidas  <br \/>\nMatt Davidson \u2013 Head of Global Brand Marketing Football  <br \/>\n<br \/>\nGonzalo Calvo \u2013 Global Director Brand Communication  <br \/>\n<br \/>\nJara Velilla \u2013 Senior Global Brand Communications Manager Football <br \/>\n<br \/>\nNikolai Ehrentraut \u2013 Manager Brand Communication Football <br \/>\n<br \/>\nPenny Pijnenburg \u2013 Senior Media Producer <br \/>\nJames Pinnington \u2013 Senior Producer  <br \/>\nGreta Bridekirk \u2013 Creative Shoot Producer  <br \/>\n<br \/>\nAdultSwim<br \/>\nJill King \u2013 SVP, Marketing and Partnerships, Adult Swim<br \/>\nEdward Poole \u2013 Sr. Director, Brand Partnerships, Adult Swim<br \/>\nErin Scruggs \u2013 Manager, Brand Partnerships, Adult Swim<br \/>\n <br \/>\nGill Austin \u2013 VP, Creative Director, Adult Swim<br \/>\nVanessa Palacios \u2013 Director of Production, Adult Swim<br \/>\nSara Hardy \u2013 Sr. Editor, Adult Swim<br \/>\nBrent Busby \u2013 Sound Designer, Adult Swim<br \/>\nAaron Weiler \u2013 Sr. Director, Adult Swim<br \/>\n <br \/>\nBrandon Lively \u2013 Creative Director, Adult Swim<br \/>\nElyse Salazar - Assoc. Art Director, Adult Swim<br \/>\nEric Nelson \u2013 Director of Production, Adult Swim","url":"https:\/\/vimeo.com\/731378604","upload_date":"2022-07-19 09:57:34","thumbnail_small":"https:\/\/i.vimeocdn.com\/video\/1472007181-73e69fc0c310e281c90338ff4d875f827199821fed7390fc7b48c00b2b94c6e8-d_100x75","thumbnail_medium":"https:\/\/i.vimeocdn.com\/video\/1472007181-73e69fc0c310e281c90338ff4d875f827199821fed7390fc7b48c00b2b94c6e8-d_200x150","thumbnail_large":"https:\/\/i.vimeocdn.com\/video\/1472007181-73e69fc0c310e281c90338ff4d875f827199821fed7390fc7b48c00b2b94c6e8-d_640","user_id":30235767,"user_name":"Elise Hagedoorn","user_url":"https:\/\/vimeo.com\/user30235767","user_portrait_small":"https:\/\/i.vimeocdn.com\/portrait\/34561054_30x30","user_portrait_medium":"https:\/\/i.vimeocdn.com\/portrait\/34561054_75x75","user_portrait_large":"https:\/\/i.vimeocdn.com\/portrait\/34561054_100x100","user_portrait_huge":"https:\/\/i.vimeocdn.com\/portrait\/34561054_300x300","stats_number_of_likes":276,"stats_number_of_plays":16742,"stats_number_of_comments":33,"duration":90,"width":1920,"height":1080,"tags":"tbwa, xspeedportal, adidas, rickandmorty, adidasfootball, speedportal, tbwa\\neboko","embed_privacy":"anywhere"},{"id":731757974,"title":"The Afterlife of Eva Hesse\u2019s \u201cExpanded Expansion\u201d","description":"This short Guggenheim-produced documentary covers the extensive research, dialogue, and complex conservation treatment that was carried out to conserve Eva Hesse\u2019s Expanded Expansion, bringing it out of storage after nearly thirty-five years. <br \/>\n<br \/>\nDespite material changes, Expanded Expansion still holds tremendous power and is a testament to a pioneering artist who, despite her untimely death in 1970, left a body of work that pushed sculpture beyond Minimalism and Abstract Expressionism, and has deeply influenced the work of younger artists.<br \/>\n<br \/>\nCurated by Lena Stringari, Deputy Director and Andrew W. Mellon Chief Conservator, with the collaboration of Richard Armstrong, Director, and Esther Chao, Objects Conservator, Eva Hesse: Expanded Expansion is on view through October 17, 2022. <br \/>\n<br \/>\nLearn more at guggenheim.org\/exhibition\/eva-hesse-expanded-expansion.","url":"https:\/\/vimeo.com\/731757974","upload_date":"2022-07-20 10:34:22","thumbnail_small":"https:\/\/i.vimeocdn.com\/video\/1472727308-ad4ac5d94bd24cfd99fc21ae00b776c82dfbdc9327275b959bab890639770bb9-d_100x75","thumbnail_medium":"https:\/\/i.vimeocdn.com\/video\/1472727308-ad4ac5d94bd24cfd99fc21ae00b776c82dfbdc9327275b959bab890639770bb9-d_200x150","thumbnail_large":"https:\/\/i.vimeocdn.com\/video\/1472727308-ad4ac5d94bd24cfd99fc21ae00b776c82dfbdc9327275b959bab890639770bb9-d_640","user_id":156414500,"user_name":"Guggenheim Museum","user_url":"https:\/\/vimeo.com\/guggenheimmuseum","user_portrait_small":"https:\/\/i.vimeocdn.com\/portrait\/65115536_30x30","user_portrait_medium":"https:\/\/i.vimeocdn.com\/portrait\/65115536_75x75","user_portrait_large":"https:\/\/i.vimeocdn.com\/portrait\/65115536_100x100","user_portrait_huge":"https:\/\/i.vimeocdn.com\/portrait\/65115536_300x300","stats_number_of_likes":142,"stats_number_of_plays":12144,"stats_number_of_comments":27,"duration":899,"width":1920,"height":1080,"tags":"New York, Guggenheim Museum, expanded expansion, museum, documentary, art conservation, art, Eva Hesse","embed_privacy":"anywhere"},{"id":728955218,"title":"Google - Young Love (Directors Cut)","description":"DIRECTOR Me<br \/>\nPRODUCTION COMPANY Love Song<br \/>\nAGENCY Wieden + Kennedy, Marc Duran & Jessica Ghersi, Marisa Bursteen, Jordan Leinen<br \/>\nACTORS Jocelyn Liu & Dagen Howard<br \/>\n<br \/>\nLA CREW:<br \/>\nDIRECTOR Justyna Obasi <br \/>\nMANAGING PARTNER Kelly Bayett <br \/>\nEXECUTIVE PRODUCER Daniel Wolfe <br \/>\nEXECUTIVE CREATIVE ASSIST Ja\u2019Lisa Arnold <br \/>\nHEAD OF PRODUCTION JP Colombo<br \/>\nPRODUCTION SUPERVISOR Matt Rudge <br \/>\nASSIST. PROD. SUPERVISOR Sara Reid, Luis Garcia <br \/>\n1ST AD Gail Shand <br \/>\nDP Kate Arizmendi <br \/>\nKEY GRIP Steve Forbes <br \/>\nGAFFER Jake Lyon <br \/>\nPRODUCTION DESIGNER JC Molina <br \/>\nART DIRECTOR Lisa Medina<br \/>\nSTYLING Astrid G<br \/>\nSCRIPT Edye Rice<br \/>\nGANG BOSS Rob Harper <br \/>\nLOCATION MANAGER Byll Williams <br \/>\n<br \/>\nNEW YORK CREW:<br \/>\nDIRECTOR Justyna Obasi <br \/>\nMANAGING PARTNER Kelly Bayett <br \/>\nEXECUTIVE PRODUCER Daniel Wolfe <br \/>\nEXECUTIVE CREATIVE ASSIST Ja\u2019Lisa Arnold <br \/>\nHEAD OF PRODUCTION JP Colombo <br \/>\nLINE PRODUCER Jose A. Barrios <br \/>\nPRODUCTION SUPERVISOR Holland Kemp <br \/>\nCOMMERCIAL COORDINATOR Zara Hayden <br \/>\n1ST AD Otis Fung <br \/>\n2nd AD David Ebel <br \/>\nDP Kate Arizmendi <br \/>\nCAMERA OPERATOR Michelle Marrion <br \/>\n1ST AC Jasmine Chang <br \/>\n2ND AC (FILM)  Helen Cassell <br \/>\n2ND AC (DIGITAL) Greg Pace<br \/>\nFILM LOADER Jade Williams<br \/>\nDIT Kazim Karaismailoglu<br \/>\nREMOTE HEAD TECH  Jack Rosenfeld <br \/>\nGAFFER Charlie McNamara <br \/>\nBB ELECTRIC Dave Hammett <br \/>\nELECTRIC Peter Marzulli, John Cardoni, Andy Clarke <br \/>\nKEY GRIP Kenny Fundus <br \/>\nBB GRIP Jackson Bosworth <br \/>\nGRIP Neil O\u2019Malley, Nick Negersmith, Holly Hosman, Chris Cazavilan <br \/>\nPRODUCTION DESIGNER Joseph Polacik <br \/>\nART COORDINATOR Darren Maxwell <br \/>\nSET DECORATOR Sara Parks<br \/>\nPROP MASTER Ben Oshman <br \/>\nPROP Jim Wessling, Joe Calderaro <br \/>\nASSIST COORDINATOR John Shashaty <br \/>\nSTUNT COORDINATOR\/DRIVER Blaise Corrigan <br \/>\nKEY RIGGER Scott Burik <br \/>\nRIGGER Bryce Burke \u2028WARDROBE STYLIST Jennifer Greene <br \/>\nWARDROBE ASSISTANT Gabrielle Ruffino <br \/>\nKEY MAKEUP Tina Murgas <br \/>\nKEY HAIR Angela Lynn Ware <br \/>\nSCRIPT SUPERVISOR Erica Lundberg <br \/>\nVTR Reggie Ollen <br \/>\nSOUND MIXER Matthew Israel\u2028BOOM OP Jason Todd<br \/>\nLOCATION MANAGER Jennifer Quesenberry <br \/>\nG&E TRUCK Terry Adams <br \/>\nVIDEO VILLAGE VAN Ata Alrafati <br \/>\nGANG BOSS \/ CAMERA TRUCK Oscar Moreira <br \/>\nGENERATOR Rich Bundy <br \/>\nTALENT MOTORHOME Sean Cummisky <br \/>\nCCO Luis Bonilla<br \/>\nCOVID ASSISTANT Xavier Barker, Danny Grajewski<br \/>\nCOVID TESTING COORDINATOR Michael Moses <br \/>\nSET MEDIC Jeruschka Argenziano <br \/>\nSET SECURITY Ricky Ingber, West Rodriguez\u2028CRAFT SERVICE Rich Hoxsey\u2028KEY PA Cha Deberry\u2028PA - DIRECTOR VAN \/ TALENT Pete Cruz\u2028PA - AGENCY VAN Jeff Javier\u2028PA - PRODUCTION CUBE Jeff Cunningham <br \/>\nPA - OFFICE Mark Califra\u2028PA - WITSTRUCK Dwayne Scott\u2028PA Owen Maldonado, Dash Porter, Gabrielle Schlein, Heinz Evander, Lani Roberts, Ryan Goldberg, Adam Rodriguez, Huston Charles<br \/>\n\u2028<br \/>\n\u2028<br \/>\n<br \/>\n\u2028<br \/>\n\u2028<br \/>\n\u2028<br \/>\n\u2028<br \/>\n<br \/>\n\u2028<br \/>\n<br \/>\n\u2028<br \/>\n\u2028<br \/>\n\u2028<br \/>\n<br \/>\n\u2028<br \/>\n\u2028<br \/>\n\u2028<br \/>\n\u2028<br \/>\n\u2028<br \/>\n<br \/>\n\u2028<br \/>\n<br \/>\n\u2028<br \/>\n<br \/>\n<br \/>\n<br \/>\n<br \/>\n<br \/>\n<br \/>\n<br \/>\n\u2028<br \/>\n<br \/>\n<br \/>\n<br \/>\n\u2028<br \/>\n<br \/>\n<br \/>\n\u2028","url":"https:\/\/vimeo.com\/728955218","upload_date":"2022-07-11 15:24:45","thumbnail_small":"https:\/\/i.vimeocdn.com\/video\/1467675638-dc5e271c75b2006201d77d2ee8ed4f8a451cb67ece9010560679d3f7e3e3d256-d_100x75","thumbnail_medium":"https:\/\/i.vimeocdn.com\/video\/1467675638-dc5e271c75b2006201d77d2ee8ed4f8a451cb67ece9010560679d3f7e3e3d256-d_200x150","thumbnail_large":"https:\/\/i.vimeocdn.com\/video\/1467675638-dc5e271c75b2006201d77d2ee8ed4f8a451cb67ece9010560679d3f7e3e3d256-d_640","user_id":22253396,"user_name":"Justyna Obasi","user_url":"https:\/\/vimeo.com\/justynaobasi","user_portrait_small":"https:\/\/i.vimeocdn.com\/portrait\/36654136_30x30","user_portrait_medium":"https:\/\/i.vimeocdn.com\/portrait\/36654136_75x75","user_portrait_large":"https:\/\/i.vimeocdn.com\/portrait\/36654136_100x100","user_portrait_huge":"https:\/\/i.vimeocdn.com\/portrait\/36654136_300x300","stats_number_of_likes":873,"stats_number_of_plays":23691,"stats_number_of_comments":28,"duration":106,"width":1920,"height":1080,"tags":"","embed_privacy":"anywhere"},{"id":729452897,"title":"Walking Gently on the Earth | A Portrait of Annie Smithers","description":"Instagram | instagram.com\/guidopezz<br \/>\nWeb | guidopezz.com<br \/>\nEmail | info@guidopezz.com<br \/>\n<br \/>\n\u201cThere was an old saying that you could feed a family on an acre of land [\u2026]\u201d<br \/>\n<br \/>\nWalking Gently on the Earth tells the story of Annie Smithers; a chef based in Lyonville, Australia whose life is dedicated to having a positive impact on the environment by treading as lightly as possible on the ground beneath her feet.<br \/>\n<br \/>\nDirected, shot and edited by Guido Pezz.<br \/>\nFeaturing Annie Smithers.<br \/>\n<br \/>\nShot in Lyonville, Australia in April 2022.","url":"https:\/\/vimeo.com\/729452897","upload_date":"2022-07-12 23:46:29","thumbnail_small":"https:\/\/i.vimeocdn.com\/video\/1473785677-eebe85f0797f8ade90bdf0409772fb45dd97a8dfa156cf628ee3c7331f15b55b-d_100x75","thumbnail_medium":"https:\/\/i.vimeocdn.com\/video\/1473785677-eebe85f0797f8ade90bdf0409772fb45dd97a8dfa156cf628ee3c7331f15b55b-d_200x150","thumbnail_large":"https:\/\/i.vimeocdn.com\/video\/1473785677-eebe85f0797f8ade90bdf0409772fb45dd97a8dfa156cf628ee3c7331f15b55b-d_640","user_id":67663535,"user_name":"Guido Pezz","user_url":"https:\/\/vimeo.com\/guidopezz","user_portrait_small":"https:\/\/i.vimeocdn.com\/portrait\/54560942_30x30?subrect=1372%2C449%2C2384%2C1461&r=cover","user_portrait_medium":"https:\/\/i.vimeocdn.com\/portrait\/54560942_75x75?subrect=1372%2C449%2C2384%2C1461&r=cover","user_portrait_large":"https:\/\/i.vimeocdn.com\/portrait\/54560942_100x100?subrect=1372%2C449%2C2384%2C1461&r=cover","user_portrait_huge":"https:\/\/i.vimeocdn.com\/portrait\/54560942_300x300?subrect=1372%2C449%2C2384%2C1461&r=cover","stats_number_of_likes":731,"stats_number_of_plays":16176,"stats_number_of_comments":45,"duration":332,"width":4096,"height":1716,"tags":"Farmer, Organic Food, Portrait, Inspirational, Environmental, Annie Smithers, Melbourne, Lyonville, Chef, Nature, People, Environmental Documentary","embed_privacy":"anywhere"},{"id":730118646,"title":"Lottusse 1877","description":"Directed by MIQUEL D\u00cdAZ PONT<br \/>\nProduced by EL D\u00cdA DESPU\u00c9S DE HOY","url":"https:\/\/vimeo.com\/730118646","upload_date":"2022-07-14 16:12:31","thumbnail_small":"https:\/\/i.vimeocdn.com\/video\/1469379200-0f13a5705f1d765974d559470ca2205f12e51a6a348ef8dd06bbaa25a7fa0824-d_100x75","thumbnail_medium":"https:\/\/i.vimeocdn.com\/video\/1469379200-0f13a5705f1d765974d559470ca2205f12e51a6a348ef8dd06bbaa25a7fa0824-d_200x150","thumbnail_large":"https:\/\/i.vimeocdn.com\/video\/1469379200-0f13a5705f1d765974d559470ca2205f12e51a6a348ef8dd06bbaa25a7fa0824-d_640","user_id":2806738,"user_name":"Pepe Gay de Li\u00e9bana","user_url":"https:\/\/vimeo.com\/pepegay","user_portrait_small":"https:\/\/i.vimeocdn.com\/portrait\/47291393_30x30?subrect=0%2C211%2C1142%2C1353&r=cover","user_portrait_medium":"https:\/\/i.vimeocdn.com\/portrait\/47291393_75x75?subrect=0%2C211%2C1142%2C1353&r=cover","user_portrait_large":"https:\/\/i.vimeocdn.com\/portrait\/47291393_100x100?subrect=0%2C211%2C1142%2C1353&r=cover","user_portrait_huge":"https:\/\/i.vimeocdn.com\/portrait\/47291393_300x300?subrect=0%2C211%2C1142%2C1353&r=cover","stats_number_of_likes":1095,"stats_number_of_plays":14280,"stats_number_of_comments":25,"duration":61,"width":1676,"height":1080,"tags":"","embed_privacy":"anywhere"},{"id":731327242,"title":"MORMOR | Far Apart","description":"Production Company - SOMESUCH<br \/>\nEP - MA\u00cbVA DEMURGER<br \/>\nMusic Video Rep - ANDR\u00c9 REID <br \/>\nProducer - ALEX CHAMBERLAIN<br \/>\nProduction Manager - ELLA KNIGHT<br \/>\nDOP - MAX PITTNER<br \/>\nStylist - LISA JARVIS<br \/>\n<br \/>\nProduction service company - SHOTINMARS<br \/>\nProducers - JULIEN MANUNTA \/ MATT BERENGUER<br \/>\nProduction coordinator - LILOU RAMAIN COLOMB<br \/>\nLocation manager - SINA FRIFRA<br \/>\nLocation manager Assitant - ELENA MANUNTA<br \/>\nRunners - TRISTAN AZHARI \/ MATHILDE BOUVARD \/ BEN SAID<br \/>\n1st Assistant Director - JEROME FRANC<br \/>\n2nd assistant Director - ELISA GERARD<br \/>\nDirector\u2019s assistant - NED BOTWOOD<br \/>\nCasting coordinator - ILONA TRAN<br \/>\nCasting - ELSA MICHON \/ JULIEN GROSSI \/ CAMILLE DELATOUR<br \/>\nExtra captain - LAETITIA FRANCARD<br \/>\n1st camera assistant - ASIA ABBATANGELO<br \/>\n2nd camera assistant - THEO FRANCHITTI<br \/>\n3rd camera assistant - MARILOU AMADEI<br \/>\nRonin Operator - CERIC VIGNIERES<br \/>\nKey Grip - NICOLAS TURCHET<br \/>\nGrips - JULIEN ROCA \/ WILDRIC LIEVIN<br \/>\nCrane technician - LOIC LAMI (THE NEXT STAGE)<br \/>\nGaffer - MICKAEL NIODO<br \/>\nElectricians - MATHIEU FRAYSSE \/ JONA BERTRAND<br \/>\nSet designer - SAMUEL HERGIBO<br \/>\nSfx - VINCENT ATHEA \/ Virginie STIE<br \/>\nMake-up artist - <br \/>\nHair stylist - SVETLANA IERSHOVA<br \/>\nWardrobe - JULIE JULIEN <br \/>\nCops wardrobe - STEPHANEZ LAGOUTTE<br \/>\nMovement director - REMY BOURCHANY<br \/>\nGraphics - Ned Botwood<br \/>\nThanks - PROVENCE STUDIOS \/ NFI \/ THE NEXT STAGE \/ LA PROD DU SUD \/ DRONECAST \/ WOONDERGRIP<br \/>\n<br \/>\nEditor - CHRIS ZIMMERMAN <br \/>\nEdit House - SEC STUDIO<br \/>\nOffline Producer - OONA EBERLE<br \/>\n<br \/>\nVFX - Daydreamer <br \/>\nCreative Director - Pete Rypstra <br \/>\nExecutive Producer - Cat Hammond <br \/>\n2D Leads - Ed Poulson & Milo Paterson<br \/>\n<br \/>\nGrade - CONNOR COOLBEAR @ ETC","url":"https:\/\/vimeo.com\/731327242","upload_date":"2022-07-19 07:10:28","thumbnail_small":"https:\/\/i.vimeocdn.com\/video\/1472092770-6d9698557446a342876f0dbcaddfa432f8763dadbd2b6517e0f4727033702f1c-d_100x75","thumbnail_medium":"https:\/\/i.vimeocdn.com\/video\/1472092770-6d9698557446a342876f0dbcaddfa432f8763dadbd2b6517e0f4727033702f1c-d_200x150","thumbnail_large":"https:\/\/i.vimeocdn.com\/video\/1472092770-6d9698557446a342876f0dbcaddfa432f8763dadbd2b6517e0f4727033702f1c-d_640","user_id":6925218,"user_name":"Camille Summers-Valli","user_url":"https:\/\/vimeo.com\/user6925218","user_portrait_small":"https:\/\/i.vimeocdn.com\/portrait\/57736880_30x30?subrect=9%2C382%2C2074%2C2447&r=cover","user_portrait_medium":"https:\/\/i.vimeocdn.com\/portrait\/57736880_75x75?subrect=9%2C382%2C2074%2C2447&r=cover","user_portrait_large":"https:\/\/i.vimeocdn.com\/portrait\/57736880_100x100?subrect=9%2C382%2C2074%2C2447&r=cover","user_portrait_huge":"https:\/\/i.vimeocdn.com\/portrait\/57736880_300x300?subrect=9%2C382%2C2074%2C2447&r=cover","stats_number_of_likes":539,"stats_number_of_plays":25627,"stats_number_of_comments":30,"duration":200,"width":3300,"height":2160,"tags":"","embed_privacy":"anywhere"},{"id":731185961,"title":"NIKE | Never Settle Never Done","description":"-NIKE | Never Settle Never Done \u2022 A film directed by Valentin Petit & produced by DIVISION for Wieden + Kennedy \u2022 Post by Monumental \u2022 VFX by Square<br \/>\n<br \/>\nCAMERA CREW<br \/>\n-Director: Valentin Petit<br \/>\n-Ex. Producer: Charlotte Lepot<br \/>\n-Producer: Benoit Roques<br \/>\n-1 AD: Cristobal Martin<br \/>\n-DOP: Paul Guilhaume<br \/>\n-DOP Film Cam:  Maeva Von Dinh<br \/>\n-1st AC Film Cam:  Georges Fromont<br \/>\n-Prod Coord :Carole Guy<br \/>\n-PA: Clara Avazeri<br \/>\n-Steadycam: Sacha Nacery<br \/>\n-Speciallised Grip: Jean Chesneau<br \/>\n-Grip: Gr\u00e9goire Benzaquen<br \/>\n-2nd AD: Cristina Freitas<br \/>\n-Stylist: Buki Ebiesuwa<br \/>\n-Wardrobe Assistant: Yahir Hernandez<br \/>\n-Bullet Time - Effigy: Vincent Haeffner & Miguel Benajes<br \/>\n-Gaffer: Carlos Melville<br \/>\n-Key Grip: Xavi Montoliu<br \/>\n-Makeup Artist: Mariona Botella<br \/>\n-Hair Artist: Xisca Heba<br \/>\n-Manicurist: Pankks<br \/>\n-Production Designer: No\u00e9 Figures<br \/>\n<br \/>\nPOST-PRODUCTION BY MONUMENTAL FX <br \/>\n-Post-Production: Germain Robin<br \/>\n-Post Production Supervisor: Laila Hammor<br \/>\n-Post Production Assistant: Alexis Diop<br \/>\n-Editor: Hugo Beron, Lola Margrain, Alexandre Sellem & Valentin Petit <br \/>\n-Editor assistants: Simon Tristant & Yanjun zhou<br \/>\n-Color Grading Arthur Paux <br \/>\n<br \/>\n<br \/>\nVFX BY SQUARE <br \/>\n-VFX Supervisor: Adrien Bavant<br \/>\n-VFX Supervisor: Flore Mounier<br \/>\n-VFX Directors: Mathieu Jussreandot & Colin Journee<br \/>\n-On-set Supervisor: Flore Mounier - bisou<br \/>\n-VFX Supervisor: Jao M\u2019Changama - bisou<br \/>\n-Production Manager: Camille Sermet<br \/>\n-Lead CG: Arthur Villiers-Moriam\u00e9<br \/>\n-3D Scan: Adrien Bavant<br \/>\n-CG artists: S\u00e9bastien Lemoignet, Yannick Large, Carlos Mendes Tavares<br \/>\n-Motion Designer: Martin Goldwasser<br \/>\n-Compositing: Thomas Jouenne, Adrien Renay, Isabelle Tchoungang<br \/>\n<br \/>\nCLIENT NIKE<br \/>\n-Nike Creative Director: Jordi Pont<br \/>\n-Nike Brand Narrative: Sam Yin Mei<br \/>\n-Nike Brand Narrative: Nicholas Vieira<br \/>\n-Nike Art Director: Vanessa Bradley<br \/>\n-Brand Narrative: Lottie Kew<br \/>\n-Nike Senior Producer Ruth Illger<br \/>\n-Nike Producer: Nili Zadok<br \/>\n-Nike Stylist: Ben Caldwell<br \/>\n-Brand Manager: Charlotte Kew<br \/>\n-Brand Manager: Weronika Budak<br \/>\n<br \/>\nAGENCY<br \/>\n-ECD :Susan Hoffman<br \/>\n-Creative: Ankita Tobit & Ben Shaffery<br \/>\n-Account Manager: Matt Whiteside<br \/>\n-MD: Katherine Thompson<br \/>\n-TV Producer: Fritha Dickie<br \/>\n-Sport Choreographer: Andy Ansah<br \/>\n-Sport Choreographer\u2019s Assist: Bohdan Pylypchuk & Marc Cumberbatch","url":"https:\/\/vimeo.com\/731185961","upload_date":"2022-07-18 19:53:00","thumbnail_small":"https:\/\/i.vimeocdn.com\/video\/1472017757-60196952078b234d7f3fbafaf974530e4abc27c0ffa0fc056ac01c7d2b9bd9b8-d_100x75","thumbnail_medium":"https:\/\/i.vimeocdn.com\/video\/1472017757-60196952078b234d7f3fbafaf974530e4abc27c0ffa0fc056ac01c7d2b9bd9b8-d_200x150","thumbnail_large":"https:\/\/i.vimeocdn.com\/video\/1472017757-60196952078b234d7f3fbafaf974530e4abc27c0ffa0fc056ac01c7d2b9bd9b8-d_640","user_id":3457566,"user_name":"valentin petit","user_url":"https:\/\/vimeo.com\/valentinpetit","user_portrait_small":"https:\/\/i.vimeocdn.com\/portrait\/19848856_30x30","user_portrait_medium":"https:\/\/i.vimeocdn.com\/portrait\/19848856_75x75","user_portrait_large":"https:\/\/i.vimeocdn.com\/portrait\/19848856_100x100","user_portrait_huge":"https:\/\/i.vimeocdn.com\/portrait\/19848856_300x300","stats_number_of_likes":1101,"stats_number_of_plays":19083,"stats_number_of_comments":25,"duration":83,"width":1920,"height":1080,"tags":"","embed_privacy":"anywhere"},{"id":730598052,"title":"\"dry\" for zara","description":"director: rubberband. <br \/>\nwriter: jason fillmore sondock<br \/>\n<br \/>\nep: sara wallace<br \/>\nproducer: josh sondock<br \/>\nproduction manager: holland kemp<br \/>\nproduction coordinator: ali lauren brody<br \/>\n<br \/>\ndp: pat golan<br \/>\nproduction designer: hans maharawal<br \/>\n<br \/>\neditor: armen harootun<br \/>\ncolorist: aubrey woodiwiss<br \/>\nsound design & mix: rapha\u00ebl ajuelos<br \/>\nmusic composition: jakob shaw<br \/>\n<br \/>\nstarring:<br \/>\ncharles: josh lovins<br \/>\njames: stephan junior <br \/>\nthalen: gavin peppers<br \/>\n<br \/>\ncasual man: geron mckinley<br \/>\nstreet man: dylan mckay<br \/>\nsophisticated man: somali findlay<br \/>\nsingle mom: aileen chang<br \/>\nbonnie: bonnie schneider<br \/>\ncaroline: carolyn harrison<br \/>\nbishop: bishop<br \/>\ndryer suit guy: jeremy david<br \/>\n<br \/>\nzara lead creative: gorka sorozabal<br \/>\nzara creatives: jae iriah, maria angeles de hita, ruben vazquez & giuseppe sartorio<br \/>\nzara producer: nerea rey<br \/>\n<br \/>\nassistant editor: victor dos santos<br \/>\n<br \/>\n1st ad: matt smith<br \/>\n2nd ad: matt hausmann<br \/>\nopa: laura belpedio<br \/>\n<br \/>\nlocation manager: john maher<br \/>\ncraft services: rich hoxsey<br \/>\ncco: luis bonilla<br \/>\ncco assistant: nelson diaz<br \/>\ncco assistant: arkene farmer-michos<br \/>\ntesting coordinator: jack leahy<br \/>\npas: maddie ross, angel flores, matt stallworth, trey davis, james berkeley, jonny rivera, charlie pingel, ruby bell, dash porter, bill gomez, al edwards<br \/>\nset medic: leslie collins<br \/>\nset security: mega<br \/>\nset security: troy tyrell<br \/>\n<br \/>\n1st ac: chevy anderson<br \/>\n2nd ac: wyatt maker<br \/>\nvtr: andrew schmetterling<br \/>\nloader: gabriel contreras<br \/>\n<br \/>\ngaffer: john cardoni<br \/>\nbest boy electric: jacob beil<br \/>\n3rd electric: neil christie<br \/>\n4th electric: gavin keenan<br \/>\n5th electric: peter caldwell<br \/>\nkey grip: paul nickason<br \/>\nbest boy grip: jon dahan<br \/>\n3rd grip: randolph rudie carty<br \/>\n4th grip: ken tanzer, esq.<br \/>\n<br \/>\nsound mixer: michael lonsdale<br \/>\nboom op: jeffrey livesey<br \/>\nscript supervisor: erica lundberg<br \/>\n<br \/>\n<br \/>\nset decorator: gabrielle rosenberg<br \/>\nleadman: chris wyatt<br \/>\nprop master: gina cimmelli<br \/>\n2nd prop: conor burke<br \/>\n3rd prop: bryant silvia<br \/>\npa: ronley fernandez<br \/>\ncarpenter: ethan long<br \/>\ncarpenter: sean mashhadian<br \/>\nconstruction grip: kurt schwarz<br \/>\nscenics: gennadi barbush & alex ibragimov<br \/>\nart director: chris dunbar<br \/>\n<br \/>\nstylist: tony irvine<br \/>\nstylist assistants: samuel deutsch, billy kiessling & stephan lacava<br \/>\ntailor: carol ai<br \/>\nhmu: tina murgas<br \/>\nhmu assistant: vanessa elese<br \/>\n<br \/>\nlead driver (camera): oscar moreira<br \/>\nglam moho driver: sean cummisky<br \/>\ng&e driver: kennyatta turner<br \/>\ngenny driver: james cisero<br \/>\npicture car driver: dermot treanor","url":"https:\/\/vimeo.com\/730598052","upload_date":"2022-07-16 11:24:16","thumbnail_small":"https:\/\/i.vimeocdn.com\/video\/1470385176-9c3dab1f0e4d8593a981091cde8d89c9e2960e82992e13622aa90c4364bab14e-d_100x75","thumbnail_medium":"https:\/\/i.vimeocdn.com\/video\/1470385176-9c3dab1f0e4d8593a981091cde8d89c9e2960e82992e13622aa90c4364bab14e-d_200x150","thumbnail_large":"https:\/\/i.vimeocdn.com\/video\/1470385176-9c3dab1f0e4d8593a981091cde8d89c9e2960e82992e13622aa90c4364bab14e-d_640","user_id":45274582,"user_name":"rubberband.","user_url":"https:\/\/vimeo.com\/rubbrband","user_portrait_small":"https:\/\/i.vimeocdn.com\/portrait\/10633000_30x30","user_portrait_medium":"https:\/\/i.vimeocdn.com\/portrait\/10633000_75x75","user_portrait_large":"https:\/\/i.vimeocdn.com\/portrait\/10633000_100x100","user_portrait_huge":"https:\/\/i.vimeocdn.com\/portrait\/10633000_300x300","stats_number_of_likes":808,"stats_number_of_plays":15209,"stats_number_of_comments":29,"duration":189,"width":1920,"height":1080,"tags":"art, short, short film, kodakshootfilm, kodak, 35mm, film, fashion, zara","embed_privacy":"anywhere"},{"id":708462756,"title":"CAROUSEL  (3x loop version)","description":"Lykke Li<br \/>\nEYEYE<br \/>\n<br \/>\nStarring: Lykke Li & Jeff Wilbusch <br \/>\n<br \/>\nDirector: Theo Lindquist<br \/>\n<br \/>\nProducer: Zane Kalnina<br \/>\nProduction Company: Common Artists<br \/>\nExecutive Producers: Anastasia Solovieva, Guy Walker<br \/>\n<br \/>\nCinematographer: Shane Ainsworth <br \/>\n<br \/>\nCasting director: Marin Hope CSA<br \/>\nWriters: Theo Lindquist, Scott Normand <br \/>\nCo-writer: Jorge Camarena<br \/>\n<br \/>\nProduction Designer: Chris Jones<br \/>\nCostume Designer: Christopher Horan<br \/>\nMakeup Artist: Ozzy Salvatierra<br \/>\nHair Stylist: Maranda Widlund<br \/>\n<br \/>\nChoreographers: Imre Van Opstal & Marne Van Opstal<br \/>\nDancers: Jessica Lee Keller, Spenser Theberge<br \/>\n<br \/>\nEditor: Theo Lindquist <br \/>\n<br \/>\n1st AD: Bettina Godi<br \/>\nProduction Manager: Blanca Balleste<br \/>\nProduction Coordinator: Ross O\u2019Shea<br \/>\n<br \/>\nBullet time System: Orbital EXP<br \/>\n<br \/>\nVFX: Patrick Conaty <br \/>\nColorist: Dante Pasquinelli<br \/>\n<br \/>\nSound mix: Shawn Everett<br \/>\nSound re-mix: Warren Brown<br \/>\n<br \/>\nGaffer: Neelix Ramirez<br \/>\n<br \/>\nBest Boy Electric: Seth Fine<br \/>\nElectricians: Vahagan Gukasyan, Zack Spencer<br \/>\nKey Grip: Jeff Allen<br \/>\nBest Boy Grip: Brandon Potter<br \/>\nCompany grips: Josue Suazo<br \/>\n<br \/>\nAssistant Art Director: Nicki Nevlin<br \/>\nSet Decorator: Neil Wyzanowski<br \/>\nProp Master: Perry Pascual<br \/>\nSet Dressers: Ben Hollander, Mike Keeper, Colton Shires, Albert Urbina<br \/>\nPainters: Nick Martinez, Manuel Rico<br \/>\n<br \/>\nCostume Designer Assistants: Charlie Burke, Lauren Jeworski<br \/>\nHair and Make Up Assistant: Olga Pirmatova<br \/>\n<br \/>\nKey PA: Michael Lira<br \/>\nSet PA: Victoria Hastings<br \/>\n<br \/>\nVFX Supervisor: Ryan McDougal<br \/>\nPre viz: Corey Belina<br \/>\nAssistant Editor: Mengyao Mia Zhang<br \/>\n<br \/>\nBehind the scenes videographer: J. Connor Bjornson <br \/>\nStills Photographer: Jonnie Chambers<br \/>\n<br \/>\nCovid Compliance Officers: Amanda Lamb, Tyrone Tyler<br \/>\nSecurity: AntiVirus Security, Carlos Robles<br \/>\nCatering: Catherine Olazabal<br \/>\nCatering Assistant: Jacob Renken<br \/>\nCraft service: Ashley Sullivan<br \/>\nLegal Services: J. Christopher Hamilton<br \/>\n<br \/>\nSpecial Thanks: Inguna Galvina, Aivars Jerumanis, Latvian Community Center, Lilly Hu, Ineta Kalnina, Helen Maier, Haley Sylvers, Sydney Sylvers, Janis Taube. Crush management: Charlie Adelman, Emily Antonicci, Jonathan Daniel, Gaby Fainsilber, Jasper Graham, Dan Kruchkow, Aaron Matusow, Bob McLynn, Lauren Papapietro, Jake Reuter, Lauren Reynaldo, Evan Taubenfeld, Brendan Walter.","url":"https:\/\/vimeo.com\/708462756","upload_date":"2022-05-10 21:45:02","thumbnail_small":"https:\/\/i.vimeocdn.com\/video\/1429543437-5e8203db1460edef5309acaa358ac0fa86827a428df7ab0f2127fffaae77118b-d_100x75","thumbnail_medium":"https:\/\/i.vimeocdn.com\/video\/1429543437-5e8203db1460edef5309acaa358ac0fa86827a428df7ab0f2127fffaae77118b-d_200x150","thumbnail_large":"https:\/\/i.vimeocdn.com\/video\/1429543437-5e8203db1460edef5309acaa358ac0fa86827a428df7ab0f2127fffaae77118b-d_640","user_id":2126133,"user_name":"THEO LINDQUIST","user_url":"https:\/\/vimeo.com\/theolindquist","user_portrait_small":"https:\/\/i.vimeocdn.com\/portrait\/43815516_30x30?subrect=1602%2C238%2C3991%2C2627&r=cover","user_portrait_medium":"https:\/\/i.vimeocdn.com\/portrait\/43815516_75x75?subrect=1602%2C238%2C3991%2C2627&r=cover","user_portrait_large":"https:\/\/i.vimeocdn.com\/portrait\/43815516_100x100?subrect=1602%2C238%2C3991%2C2627&r=cover","user_portrait_huge":"https:\/\/i.vimeocdn.com\/portrait\/43815516_300x300?subrect=1602%2C238%2C3991%2C2627&r=cover","duration":108,"width":4096,"height":2458,"tags":"","embed_privacy":"anywhere"},{"id":729145479,"title":"Ummet Ozcan \/ Oblivion","description":"About the Work<br \/>\nWOW has produced a music video for \u201cOblivion,\u201d the new tune by Ummet Ozcan, an EDM producer\/DJ based in the Netherlands. In order to express the tune's uneasy atmosphere, we created a video on the theme of \u201cthe human body as a pattern.\u201d<br \/>\n<br \/>\n<br \/>\n\u4f5c\u54c1\u306b\u3064\u3044\u3066<br \/>\n\u30aa\u30e9\u30f3\u30c0\u3092\u62e0\u70b9\u306b\u6d3b\u52d5\u3059\u308bEDM\u30d7\u30ed\u30c7\u30e5\u30fc\u30b5\u30fc\uff0fDJ\u3001Ummet Ozcan\uff08\u30a6\u30e1\u30c3\u30c8\u30fb\u30aa\u30ba\u30ab\u30f3\uff09\u306e\u65b0\u4f5c \u300cOblivion\u300d\u306eMV\u3092\u5236\u4f5c\u3002\u66f2\u306e\u6301\u3064\u602a\u3057\u3052\u306a\u96f0\u56f2\u6c17\u3092\u8868\u73fe\u3059\u308b\u70ba\u3001\u300c\u6a21\u69d8\u3068\u3057\u3066\u306e\u4eba\u4f53\u300d\u3092\u30c6\u30fc\u30de\u306b\u6620\u50cf\u3092\u5236\u4f5c\u3057\u305f\u3002<br \/>\n<br \/>\n<br \/>\nStaff<br \/>\nDirector \/ CG Designer\uff1a Kouhei Nakama<br \/>\nProducer \uff1a Ko Yamamoto","url":"https:\/\/vimeo.com\/729145479","upload_date":"2022-07-12 05:37:12","thumbnail_small":"https:\/\/i.vimeocdn.com\/video\/1467676549-b24ddd11669b131280a9eb3512873b459d8cd960bceb970f3ca051f5c95a24a7-d_100x75","thumbnail_medium":"https:\/\/i.vimeocdn.com\/video\/1467676549-b24ddd11669b131280a9eb3512873b459d8cd960bceb970f3ca051f5c95a24a7-d_200x150","thumbnail_large":"https:\/\/i.vimeocdn.com\/video\/1467676549-b24ddd11669b131280a9eb3512873b459d8cd960bceb970f3ca051f5c95a24a7-d_640","user_id":7923368,"user_name":"WOW inc.","user_url":"https:\/\/vimeo.com\/wowinc","user_portrait_small":"https:\/\/i.vimeocdn.com\/portrait\/4703572_30x30","user_portrait_medium":"https:\/\/i.vimeocdn.com\/portrait\/4703572_75x75","user_portrait_large":"https:\/\/i.vimeocdn.com\/portrait\/4703572_100x100","user_portrait_huge":"https:\/\/i.vimeocdn.com\/portrait\/4703572_300x300","stats_number_of_likes":399,"stats_number_of_plays":13890,"stats_number_of_comments":37,"duration":204,"width":1920,"height":1080,"tags":"","embed_privacy":"anywhere"}]